{
  "project_info": {
    "project_number": "938799579766",
    "firebase_url": "https://absis-capital-sync-default-rtdb.asia-southeast1.firebasedatabase.app",
    "project_id": "absis-capital-sync",
    "storage_bucket": "absis-capital-sync.firebasestorage.app"
  },
  "client": [
    {
      "client_info": {
        "mobilesdk_app_id": "1:938799579766:android:061665ee2f6476b26ad557",
        "android_client_info": {
          "package_name": "com.absis.capitalsync"
        }
      },
      "oauth_client": [
        {
          "client_id": "938799579766-55mheguj6eagojrcgbehnvrjm9mevk42.apps.googleusercontent.com",
          "client_type": 3
        }
      ],
      "api_key": [
        {
          "current_key": "AIzaSyBjMHLK2tjoqiX6IlJbU3yAXR3YKHtKKLA"
        }
      ],
      "services": {
        "appinvite_service": {
          "other_platform_oauth_client": [
            {
              "client_id": "938799579766-55mheguj6eagojrcgbehnvrjm9mevk42.apps.googleusercontent.com",
              "client_type": 3
            }
          ]
        }
      }
    }
  ],
  "configuration_version": "1"
}